thermontfa/__init__.py
thermontfa/tabular_interpolation.py
thermontfa/thermoNTFA.py
thermontfa-0.1.0.dist-info/LICENSE
thermontfa-0.1.0.dist-info/METADATA
thermontfa-0.1.0.dist-info/WHEEL
thermontfa-0.1.0.dist-info/top_level.txt
thermontfa-0.1.0.dist-info/RECORD
