Metadata-Version: 2.1
Name: thermontfa
Version: 0.1.0
Author-email: Felix Fritzen <fritzen@simtech.uni-stuttgart.de>, Julius Herb <julius.herb@mib.uni-stuttgart.de>, Shadi Sharba <shadi.sharba@isc.fraunhofer.de>
License: CC-BY-4.0
Keywords: NTFA,MOR,mechanics,composite materials,temperature-dependence,multi-scale,plasticity
Classifier: Programming Language :: Python :: 3
Classifier: License :: OSI Approved :: MIT License
Classifier: Operating System :: OS Independent
Requires-Python: >=3.10
License-File: LICENSE
Requires-Dist: numpy ~=1.26.4
Requires-Dist: h5py ~=3.11.0
Requires-Dist: matplotlib ~=3.8.4
Provides-Extra: all
Requires-Dist: fnocg[dev,etc] ; extra == 'all'
Provides-Extra: dev
Requires-Dist: jupyterlab ~=4.2.0 ; extra == 'dev'
Requires-Dist: jupytext ~=1.16.2 ; extra == 'dev'
Requires-Dist: pre-commit ~=3.7.1 ; extra == 'dev'
Requires-Dist: pytest ~=8.2.0 ; extra == 'dev'
Requires-Dist: sphinx ; extra == 'dev'
Requires-Dist: myst-parser ~=3.0.1 ; extra == 'dev'
Requires-Dist: nbsphinx ~=0.9.4 ; extra == 'dev'
Requires-Dist: sphinx-gallery ~=0.16.0 ; extra == 'dev'
Requires-Dist: sphinx-rtd-theme ~=2.0.0 ; extra == 'dev'
Provides-Extra: etc
